bondcomp/__init__.py
bondcomp/bondcomp.py
bondcomp-0.2.0.data/scripts/get_bench.py
bondcomp-0.2.0.dist-info/DESCRIPTION.rst
bondcomp-0.2.0.dist-info/METADATA
bondcomp-0.2.0.dist-info/RECORD
bondcomp-0.2.0.dist-info/WHEEL
bondcomp-0.2.0.dist-info/metadata.json
bondcomp-0.2.0.dist-info/top_level.txt
