Metadata-Version: 2.0
Name: bondcomp
Version: 0.2.0
Summary: Bond benchmark suggestions.
Home-page: https://github.com/rolfantlers
Author: Anders Amundson
Author-email: amundson@gmail.com
License: MIT
Platform: UNKNOWN
Requires-Dist: datetime
Requires-Dist: nose
